MANIFEST.in
README.md
setup.py
example/__init__.py
example/example.py
example/main.py
mk_pyproject/__init__.py
mk_pyproject/__main__.py
mk_pyproject/exceptions.py
mk_pyproject/render.py
mk_pyproject.egg-info/PKG-INFO
mk_pyproject.egg-info/SOURCES.txt
mk_pyproject.egg-info/dependency_links.txt
mk_pyproject.egg-info/entry_points.txt
mk_pyproject.egg-info/top_level.txt
templates/__init__.py
version/__init__.py
version/__version__.py