Metadata-Version: 2.1
Name: mk-pyproject
Version: 0.0.1.1
Summary: create Python Project Template
Home-page: https://github.com/chengcxy/mk_pyproject
Author: chengxinyao
Author-email: chengxinyao1991@163.com
License: MIT
Project-URL: Source, https://github.com/chengcxy/mk_pyproject
Keywords: python project structures
Platform: any
Classifier: Development Status :: 3 - Alpha
Classifier: Intended Audience :: Developers
Classifier: License :: OSI Approved :: MIT License
Classifier: Programming Language :: Python :: 3
Classifier: Programming Language :: Python :: 3.3
Classifier: Programming Language :: Python :: 3.4
Classifier: Programming Language :: Python :: 3.5
Classifier: Programming Language :: Python :: 3.6
Classifier: Programming Language :: Python :: 3.7
Classifier: Topic :: Software Development :: Libraries :: Python Modules
